maubot/__init__.py
maubot/__main__.py
maubot/__meta__.py
maubot/client.py
maubot/config.py
maubot/example-config.yaml
maubot/instance.py
maubot/matrix.py
maubot/plugin_base.py
maubot/plugin_server.py
maubot/py.typed
maubot/scheduler.py
maubot/server.py
maubot/cli/__init__.py
maubot/cli/__main__.py
maubot/cli/base.py
maubot/cli/config.py
maubot/cli/cliq/__init__.py
maubot/cli/cliq/cliq.py
maubot/cli/cliq/validators.py
maubot/cli/commands/__init__.py
maubot/cli/commands/auth.py
maubot/cli/commands/build.py
maubot/cli/commands/init.py
maubot/cli/commands/login.py
maubot/cli/commands/logs.py
maubot/cli/commands/upload.py
maubot/cli/res/config.yaml
maubot/cli/res/maubot.yaml.j2
maubot/cli/res/plugin.py.j2
maubot/cli/res/spdx.json.zip
maubot/cli/util/__init__.py
maubot/cli/util/spdx.py
maubot/db/__init__.py
maubot/db/client.py
maubot/db/instance.py
maubot/db/upgrade/__init__.py
maubot/db/upgrade/v01_initial_revision.py
maubot/db/upgrade/v02_instance_database_engine.py
maubot/handlers/__init__.py
maubot/handlers/command.py
maubot/handlers/event.py
maubot/handlers/web.py
maubot/lib/__init__.py
maubot/lib/color_log.py
maubot/lib/future_awaitable.py
maubot/lib/optionalalchemy.py
maubot/lib/plugin_db.py
maubot/lib/state_store.py
maubot/lib/zipimport.py
maubot/loader/__init__.py
maubot/loader/abc.py
maubot/loader/meta.py
maubot/loader/zip.py
maubot/management/__init__.py
maubot/management/api/__init__.py
maubot/management/api/auth.py
maubot/management/api/base.py
maubot/management/api/client.py
maubot/management/api/client_auth.py
maubot/management/api/client_proxy.py
maubot/management/api/dev_open.py
maubot/management/api/instance.py
maubot/management/api/instance_database.py
maubot/management/api/log.py
maubot/management/api/login.py
maubot/management/api/middleware.py
maubot/management/api/plugin.py
maubot/management/api/plugin_upload.py
maubot/management/api/responses.py
maubot/management/frontend/build/asset-manifest.json
maubot/management/frontend/build/favicon.png
maubot-0.5.2.dist-info/LICENSE
maubot-0.5.2.dist-info/METADATA
maubot-0.5.2.dist-info/WHEEL
maubot-0.5.2.dist-info/entry_points.txt
maubot-0.5.2.dist-info/top_level.txt
maubot-0.5.2.dist-info/RECORD
