Metadata-Version: 2.2
Name: maubot
Version: 0.5.2
Summary: A plugin-based Matrix bot system.
Home-page: https://github.com/maubot/maubot
Author: Tulir Asokan
Author-email: tulir@maunium.net
Project-URL: Changelog, https://github.com/maubot/maubot/blob/master/CHANGELOG.md
Classifier: Development Status :: 4 - Beta
Classifier: License :: OSI Approved :: GNU Affero General Public License v3 or later (AGPLv3+)
Classifier: Topic :: Communications :: Chat
Classifier: Framework :: AsyncIO
Classifier: Programming Language :: Python
Classifier: Programming Language :: Python :: 3
Classifier: Programming Language :: Python :: 3.10
Classifier: Programming Language :: Python :: 3.11
Classifier: Programming Language :: Python :: 3.12
Classifier: Programming Language :: Python :: 3.13
Requires-Python: ~=3.10
License-File: LICENSE
Requires-Dist: mautrix<0.21,>=0.20.7
Requires-Dist: aiohttp<4,>=3
Requires-Dist: yarl<2,>=1
Requires-Dist: asyncpg<1,>=0.20
Requires-Dist: aiosqlite<1,>=0.16
Requires-Dist: commonmark<1,>=0.9
Requires-Dist: ruamel.yaml<0.19,>=0.15.35
Requires-Dist: attrs>=18.1.0
Requires-Dist: bcrypt<5,>=3
Requires-Dist: packaging>=10
Requires-Dist: click<9,>=7
Requires-Dist: colorama<0.5,>=0.4
Requires-Dist: questionary<3,>=1
Requires-Dist: jinja2<4,>=2
Requires-Dist: setuptools
Provides-Extra: encryption
Requires-Dist: pycryptodome<4,>=3; extra == "encryption"
Requires-Dist: python-olm<4,>=3; extra == "encryption"
Requires-Dist: unpaddedbase64<3,>=1; extra == "encryption"
Provides-Extra: testing
Requires-Dist: pytest; extra == "testing"
Requires-Dist: pytest-asyncio; extra == "testing"
Provides-Extra: legacydb
Requires-Dist: SQLAlchemy<1.4,>1; extra == "legacydb"
Provides-Extra: all
Requires-Dist: SQLAlchemy<1.4,>1; extra == "all"
Requires-Dist: pycryptodome<4,>=3; extra == "all"
Requires-Dist: pytest; extra == "all"
Requires-Dist: pytest-asyncio; extra == "all"
Requires-Dist: python-olm<4,>=3; extra == "all"
Requires-Dist: unpaddedbase64<3,>=1; extra == "all"
Dynamic: author
Dynamic: author-email
Dynamic: classifier
Dynamic: description
Dynamic: description-content-type
Dynamic: home-page
Dynamic: project-url
Dynamic: provides-extra
Dynamic: requires-dist
Dynamic: requires-python
Dynamic: summary
